dag_cbor/__init__.py
dag_cbor/ipld.py
dag_cbor/py.typed
dag_cbor/random.py
dag_cbor/decoding/__init__.py
dag_cbor/decoding/_err.py
dag_cbor/decoding/_err_utils.py
dag_cbor/decoding/_stream.py
dag_cbor/decoding/err.py
dag_cbor/encoding/__init__.py
dag_cbor/encoding/err.py
makkus.dag_cbor-0.3.4.dist-info/LICENSE
makkus.dag_cbor-0.3.4.dist-info/METADATA
makkus.dag_cbor-0.3.4.dist-info/WHEEL
makkus.dag_cbor-0.3.4.dist-info/top_level.txt
makkus.dag_cbor-0.3.4.dist-info/RECORD
